pypkgs_ktan/__init__.py
pypkgs_ktan/pypkgs_ktan.py
pypkgs_ktan-0.1.0.dist-info/LICENSE
pypkgs_ktan-0.1.0.dist-info/WHEEL
pypkgs_ktan-0.1.0.dist-info/METADATA
pypkgs_ktan-0.1.0.dist-info/RECORD
