Metadata-Version: 2.1
Name: pypkgs-ktan
Version: 0.1.0
Summary: Individual assignment 1 Python package
License: MIT
Author: tan95
Author-email: andrew--tan@outlook.com
Requires-Python: >=3.7.1,<4.0
Classifier: License :: OSI Approved :: MIT License
Classifier: Programming Language :: Python :: 3
Classifier: Programming Language :: Python :: 3.8
Classifier: Programming Language :: Python :: 3.9
Requires-Dist: pandas (>=1.2.2,<2.0.0)
